{
   "items": [
       {"type": "video", "item_id": "E3oqM8P4J7Q", "title": "Ten Years of Euphoria CD1" },
       {"type": "video", "item_id": "cHDCFp-JtqQ", "title": "Ten Years of Euphoria CD2" },
       {"type": "video", "item_id": "VVQiVYOG25U", "title": "Ibiza Euphoria CD1" },
       {"type": "video", "item_id": "wtoWLoZpU_w", "title": "Ibiza Euphoria CD2" },
       {"type": "video", "item_id": "j3ukRL1Oozs", "title": "Deeper Euphoria CD1" },
       {"type": "video", "item_id": "JTAW2y_zcbg", "title": "Deeper Euphoria CD2" },
       {"type": "video", "item_id": "9andBkkpXxA", "title": "Absolute Euphoria CD2" },
       {"type": "video", "item_id": "UmrJ6_6_VcU", "title": "Total Euphoria CD2" },
       {"type": "video", "item_id": "jwkpb3Up648", "title": "Pure Euphoria CD1" },
       {"type": "video", "item_id": "9kJxkbJnJwU", "title": "Pure Euphoria CD2" },
       {"type": "video", "item_id": "KLjNkLVH74I", "title": "Chilled Euphoria CD1" }
   ]
}

